<?xml version='1.0' encoding='utf-8'?><m:page id='e000f5cd-e0af-4a3d-ac7d-45b38e8d3953' xmlns='http://www.w3.org/1999/xhtml' title='Page Title' class='layout-atlas' xmlns:m='http://schemas.mendix.com/forms/1.0'><m:layouts><m:layout path='ZipcodeHousenumber/Atlas_Default.layout.xml'></m:layout></m:layouts><m:arguments><m:argument parameterName='5ea8b06e-771d-46e2-8c0c-95e85bbbf0e9'><div data-mendix-id='10_0' class='mx-layoutgrid mx-layoutgrid-fluid container-fluid mx-name-layoutGrid1'><div class='row'><div class='col-md-12'><div data-mendix-id='10_1' data-mendix-type='mxui.widget.ReactWidgetWrapper' data-mendix-props='"widgetTree":{"widget":"com.mendix.widget.core.Text","widgetId":"10_1","props":{"name":"text1","class":"mx-name-text1","style":{},"caption":{"$type":"DynamicTextProperty","text":{"text":"Tekst","friendlyId":"ZipcodeHousenumber.Home.text1"}},"renderMode":"span"},"children":[]}'></div><div data-mendix-id='10_2' data-mendix-type='mxui.widget.DataView' data-mendix-props='"friendlyId":"ZipcodeHousenumber.Home.dataViewAddress","entity":"ZipcodeHousenumber.Address","schema":"50f14539-ad45-4c2d-98a9-642d30c3b5ff","datasource":{"friendlyId":"ZipcodeHousenumber.Home.dataViewAddress","type":"microflow","microflow":"ZipcodeHousenumber.ACT_Address_CreateEmptyObject","path":"ZipcodeHousenumber.Address","parameters":[]}' class='mx-name-dataViewAddress form-horizontal' tabindex='0'></div></div></div><div class='row'><div class='col-md-12'></div></div></div></m:argument></m:arguments><m:templates><m:template widget-id='10_2' name='content'><div data-mendix-id='10_4' class='form-group mx-name-textBox3'><label class='control-label col-sm-3'>Country</label><div class='col-sm-9'><div data-mendix-id='10_17' data-mendix-type='mxui.widget.TextInput' data-mendix-props='"friendlyId":"ZipcodeHousenumber.Home.textBox3","insideFormGroup":true,"attributePath":"ZipcodeHousenumber.Address/Country","readOnlyStyle":"control","validation":null,"placeholder":"","maxLength":10' tabindex='0'></div></div></div><div data-mendix-id='10_5' class='form-group mx-name-textBox4'><label class='control-label col-sm-3'>Postalcode</label><div class='col-sm-9'><div data-mendix-id='10_18' data-mendix-type='mxui.widget.TextInput' data-mendix-props='"friendlyId":"ZipcodeHousenumber.Home.textBox4","insideFormGroup":true,"attributePath":"ZipcodeHousenumber.Address/Postalcode","readOnlyStyle":"control","validation":null,"events":{"change":{"name":"ZipcodeHousenumber.ACT_Call_Address_GetSingleAddress","validate":"view","applyTo":"selection","allowedRoles":["Administrator","User"]}},"placeholder":"","maxLength":200' tabindex='0'></div></div></div><div data-mendix-id='10_6' class='form-group mx-name-textBox5'><label class='control-label col-sm-3'>Housenumber</label><div class='col-sm-9'><div data-mendix-id='10_19' data-mendix-type='mxui.widget.NumberInput' data-mendix-props='"friendlyId":"ZipcodeHousenumber.Home.textBox5","insideFormGroup":true,"attributePath":"ZipcodeHousenumber.Address/Housenumber","readOnlyStyle":"control","validation":null,"events":{"change":{"name":"ZipcodeHousenumber.ACT_Call_Address_GetSingleAddress","validate":"view","applyTo":"selection","allowedRoles":["Administrator","User"]}},"placeholder":""' tabindex='0'></div></div></div><div data-mendix-id='10_7' class='form-group mx-name-textBox6'><label class='control-label col-sm-3'>Extension</label><div class='col-sm-9'><div data-mendix-id='10_20' data-mendix-type='mxui.widget.TextInput' data-mendix-props='"friendlyId":"ZipcodeHousenumber.Home.textBox6","insideFormGroup":true,"attributePath":"ZipcodeHousenumber.Address/HousenumberExtension","readOnlyStyle":"control","validation":null,"events":{"change":{"name":"ZipcodeHousenumber.ACT_Call_Address_GetSingleAddress","progress":{"message":"Retrieving street, city and location based on current addressdata","modal":false},"validate":"view","applyTo":"selection","allowedRoles":["Administrator","User"]}},"placeholder":"","maxLength":20' tabindex='0'></div></div></div></m:template><m:template widget-id='10_2' name='footer'><div data-mendix-id='10_9' data-mendix-type='mxui.widget.ActionButton' data-mendix-props='"friendlyId":"ZipcodeHousenumber.Home.actionButton2","caption":{"text":"Opslaan","friendlyId":"ZipcodeHousenumber.Home.actionButton2"},"renderType":"button","action":{"type":"saveChanges","hasParameter":true,"params":{"closePage":true}}' class='mx-name-actionButton2 btn-success' tabindex='0'></div><div data-mendix-id='10_10' data-mendix-type='mxui.widget.ActionButton' data-mendix-props='"friendlyId":"ZipcodeHousenumber.Home.actionButton3","caption":{"text":"Annuleren","friendlyId":"ZipcodeHousenumber.Home.actionButton3"},"renderType":"button","action":{"type":"cancelChanges","hasParameter":false,"params":{"closePage":true}}' class='mx-name-actionButton3 btn-default' tabindex='0'></div><div data-mendix-id='10_11' data-mendix-type='mxui.widget.ActionButton' data-mendix-props='"friendlyId":"ZipcodeHousenumber.Home.actionButtonGetAddressData","caption":{"text":"AC t get address data","friendlyId":"ZipcodeHousenumber.Home.actionButtonGetAddressData"},"renderType":"button","action":{"type":"callMicroflow","hasParameter":true,"params":{"name":"ZipcodeHousenumber.ACT_Call_Address_GetSingleAddress","validate":"view","applyTo":"selection","allowedRoles":["Administrator","User"]}}' data-mendix-roles='Administrator,User' class='mx-name-actionButtonGetAddressData btn-default' tabindex='0'></div><div data-mendix-id='10_12' data-mendix-type='mxui.widget.ReactWidgetWrapper' data-mendix-props='"widgetTree":{"widget":"com.mendix.widget.core.Text","widgetId":"10_12","props":{"name":"textSelecetedAddress","class":"mx-name-textSelecetedAddress","style":{},"caption":{"$type":"DynamicTextProperty","text":{"text":"Tekst","friendlyId":"ZipcodeHousenumber.Home.textSelecetedAddress"}},"renderMode":"span"},"children":[]}'></div><div data-mendix-id='10_13' class='form-group mx-name-textBox10'><label class='control-label col-sm-3'>City</label><div class='col-sm-9'><div data-mendix-id='10_21' data-mendix-type='mxui.widget.TextInput' data-mendix-props='"friendlyId":"ZipcodeHousenumber.Home.textBox10","insideFormGroup":true,"attributePath":"ZipcodeHousenumber.Address/City","readOnlyStyle":"control","validation":null,"placeholder":"","maxLength":200' tabindex='0'></div></div></div><div data-mendix-id='10_14' class='form-group mx-name-textBox11'><label class='control-label col-sm-3'>Street</label><div class='col-sm-9'><div data-mendix-id='10_22' data-mendix-type='mxui.widget.TextInput' data-mendix-props='"friendlyId":"ZipcodeHousenumber.Home.textBox11","insideFormGroup":true,"attributePath":"ZipcodeHousenumber.Address/Street","readOnlyStyle":"control","validation":null,"placeholder":"","maxLength":200' tabindex='0'></div></div></div><div data-mendix-id='10_15' class='form-group mx-name-textBox12'><label class='control-label col-sm-3'>Longitude</label><div class='col-sm-9'><div data-mendix-id='10_23' data-mendix-type='mxui.widget.NumberInput' data-mendix-props='"friendlyId":"ZipcodeHousenumber.Home.textBox12","insideFormGroup":true,"attributePath":"ZipcodeHousenumber.Address/Longitude","readOnlyStyle":"control","validation":null,"placeholder":"","precision":2' tabindex='0'></div></div></div><div data-mendix-id='10_16' class='form-group mx-name-textBox9'><label class='control-label col-sm-3'>Latitude</label><div class='col-sm-9'><div data-mendix-id='10_24' data-mendix-type='mxui.widget.NumberInput' data-mendix-props='"friendlyId":"ZipcodeHousenumber.Home.textBox9","insideFormGroup":true,"attributePath":"ZipcodeHousenumber.Address/Latitude","readOnlyStyle":"control","validation":null,"placeholder":"","precision":2' tabindex='0'></div></div></div></m:template></m:templates></m:page>